{
  "powers": [
    "project_vor:kraken/height_4_5b",
    "project_vor:kraken/stickiness",
    "project_vor:kraken/convert/2",
    "project_vor:kraken/bind",
    "project_vor:kraken/health_up/4",
    "project_vor:kraken/charge",

    "origins:water_breathing",
    "project_vor:kraken/water_vision_no_toggle",
    "origins:aqua_affinity",
    "origins:like_water",
    "origins:aquatic",
    "origins:conduit_power_on_land"
  ],
  "icon": {
    "item": "minecraft:glow_squid_spawn_egg"
  },
  "order": 4,
  "impact": 2,
  "name": "ยง4The Kraken",
  "description": "The rest is silence.",
  "unchoosable": true
}
